formal/__init__.py
formal/sqlcommenter/__init__.py
formal/sqlcommenter/psycopg2/__init__.py
formal/sqlcommenter/psycopg2/extension.py
tests/generic/__init__.py
tests/generic/test_generate_sql_comment.py
tests/psycopg2/__init__.py
tests/psycopg2/tests.py
formal_sqlcommenter-1.0.6.dist-info/METADATA
formal_sqlcommenter-1.0.6.dist-info/WHEEL
formal_sqlcommenter-1.0.6.dist-info/top_level.txt
formal_sqlcommenter-1.0.6.dist-info/RECORD
