Metadata-Version: 2.1
Name: formal-sqlcommenter
Version: 1.0.6
Summary: Formal sql commenter
Home-page: https://github.com/formalco/sqlcommenter
Author: Formal
Author-email: hello@joinformal.com
License: BSD
Keywords: postgresql sql database
Platform: UNKNOWN
Classifier: Environment :: Web Environment
Classifier: Intended Audience :: Developers
Classifier: License :: OSI Approved :: BSD License
Classifier: Operating System :: OS Independent
Classifier: Programming Language :: Python :: 3
Classifier: Programming Language :: Python :: 3.6
Classifier: Programming Language :: Python :: 3.7
Classifier: Programming Language :: Python :: 3.8
Classifier: Programming Language :: Python :: 3.9
Classifier: Topic :: Utilities
Provides-Extra: psycopg2
Requires-Dist: psycopg2 ; extra == 'psycopg2'
